{
  "generator-jhipster": {
    "baseName": "helix",
    "packageName": "com.helix",
    "packageFolder": "com/helix",
    "authenticationType": "session",
    "hibernateCache": "ehcache",
    "clusteredHttpSession": "no",
    "websocket": "no",
    "databaseType": "sql",
    "devDatabaseType": "postgresql",
    "prodDatabaseType": "postgresql",
    "searchEngine": "elasticsearch",
    "useCompass": false,
    "buildTool": "maven",
    "frontendBuilder": "grunt",
    "javaVersion": "8",
    "enableTranslation": true,
    "rememberMeKey": "96a3636fc65afd8094afb8745b304dcabad3c821"
  }
}